{"stats":{"minecraft:picked_up":{"minecraft:stone_slab":1,"minecraft:cobbled_deepslate":501,"minecraft:shulker_box":1,"minecraft:diamond_pickaxe":9},"minecraft:used":{"minecraft:diamond_pickaxe":8573},"minecraft:custom":{"minecraft:time_since_rest":0,"minecraft:damage_taken":2104,"minecraft:leave_game":8,"minecraft:play_time":90761,"minecraft:walk_one_cm":489,"minecraft:time_since_death":0,"minecraft:deaths":8,"minecraft:total_world_time":90761,"minecraft:drop":2,"minecraft:fly_one_cm":136},"minecraft:broken":{"minecraft:diamond_pickaxe":1},"minecraft:dropped":{"minecraft:diamond_pickaxe":2},"minecraft:killed_by":{"minecraft:player":8},"minecraft:mined":{"minecraft:cobbled_deepslate":8566,"minecraft:hopper":6,"minecraft:stone_slab":1}},"DataVersion":3337}